wc/__init__.py
wc/genCover.py
atscrusher-0.0.3.dist-info/LICENSE
atscrusher-0.0.3.dist-info/METADATA
atscrusher-0.0.3.dist-info/WHEEL
atscrusher-0.0.3.dist-info/top_level.txt
atscrusher-0.0.3.dist-info/RECORD
