Metadata-Version: 2.1
Name: atscrusher
Version: 0.0.3
Summary: A package designed to process language related to prgessing your job search. Developed by renanm.b3@gmail.com and anthonycavuoti@gmail.com.
Home-page: https://github.com/pypa/sampleproject
Author: Anthony Cavuoti and Renanm Barbosa
Author-email: anthonycavuoti@gmail.com
License: UNKNOWN
Project-URL: Bug Tracker, https://github.com/pypa/sampleproject/issues
Platform: UNKNOWN
Classifier: Programming Language :: Python :: 3
Classifier: License :: OSI Approved :: MIT License
Classifier: Operating System :: OS Independent
Requires-Python: >=3.6
License-File: LICENSE
Requires-Dist: openai
